qdrant_tools/README.md
qdrant_tools/__init__.py
qdrant_tools/requirements.txt
qdrant_tools/vectordb.py
qdrant_tools-0.0.4.dist-info/LICENSE
qdrant_tools-0.0.4.dist-info/METADATA
qdrant_tools-0.0.4.dist-info/WHEEL
qdrant_tools-0.0.4.dist-info/RECORD
