Metadata-Version: 2.1
Name: qdrant-tools
Version: 0.0.4
Summary: 
License: MIT
Author: NirantK
Author-email: nirant.bits@gmail.com
Requires-Python: >=3.8,<3.12
Classifier: License :: OSI Approved :: MIT License
Classifier: Programming Language :: Python :: 3
Classifier: Programming Language :: Python :: 3.8
Classifier: Programming Language :: Python :: 3.9
Classifier: Programming Language :: Python :: 3.10
Classifier: Programming Language :: Python :: 3.11
Requires-Dist: pinecone-client (>=2.2.2,<3.0.0)
Requires-Dist: qdrant-client (>=1.2.0,<2.0.0)
